<?xml version="1.0" encoding="utf-8" ?>
<localize>
  <umbTextpage id="2016043012" parentID="18486" level="4" writerID="106" creatorID="106" nodeType="1059" template="13" sortOrder="36" createDate="2015-05-13T15:16:30" updateDate="2015-05-13T15:16:30" nodeName="ipinyou" urlName="ipinyou" writerName="content" creatorName="content" path="-1,11978,19421,18486,2016043012" isDoc="">
    <bodyText>
      <![CDATA[
            <div class="common-content-bookmark">
                        
                <div class="section-component">
                    <p><b>* 此案例基于在全球其他地区由微软运营的 Microsoft Azure 云平台实施，仅供由世纪互联运营的 Microsoft Azure 客户参考。</b></p>
                    <h2>概述</h2>
                    <p>Cortana 智能系统及 Azure IoT 套件能为劳斯莱斯飞行人员提供发动机效率、天气状况、航线和原定着陆计划等有效信息。通过先进的数据分析服务及物联网管理平台，实时提供操作建议，包括如何提供引擎性能和操作效率等，节约燃料预测维修需求，减少代价高昂的停机检测和延误时间，从而减少库存成本，提高可用性，实现效能最大化，为客户带来安全高效的乘车体验。随着 Cortana 智能系统业务的不断发展，未来在 Azure 中国也会逐步上市。</p>
                    
                </div>  
                <div class="tag-list">
                    <p class="p">
                        <h2>所用技术和服务</h2>											
                        <ul class="link-group-icon">
							<li><img src="//wacnppe.blob.core.chinacloudapi.cn/marketing-resource/css/service_icon_24_IoT-Suite.png"><a target="_blank" href="/home/features/iot-suite/" id="case-study_rolls-royce_iot-suite">Azure IoT 套件</a></li>
                            <li>Cortana 智能系统</li>
                        </ul>
                    </p>
                </div>
            </div>

            ]]>
    </bodyText>
    <umbracoNaviHide>0</umbracoNaviHide>
    <pageTitle>劳斯莱斯-Azure云计算</pageTitle>
    <metaKeywords>劳斯莱斯Azure 合作案例</metaKeywords>
    <metaDescription><![CDATA[劳斯莱斯利用 Cortana 人工智能系统及 Azure IoT 套件远程数据分析，实现效能最大化。通过 Cortana 人工智能系统及 Azure IoT 套件提供的先进的数据分析服务及物联网管理平台和实时操作建议，节约了燃料预测维修需求，减少了代价高昂的停机检测和延误时间，从而减少库存成本，提高可用性，实现效能最大化，为客户带来安全高效的乘车体验。
]]></metaDescription>
    <linkid>case-studies-rolls-royce</linkid>
    <urlDisplayName>劳斯莱斯</urlDisplayName>
    <headerExpose></headerExpose>
    <footerExpose></footerExpose>
    <banner><![CDATA[
      <!-- BEGIN: Banner -->
         <div class="common-banner casestudy-banner" data-config="{'backgroundColor':'#333333', 'backgroundImage':'//wacnppe.blob.core.chinacloudapi.cn/marketing-resource/media/images/casestudy/banner/case-study-default-banner.jpg','imageHeight':'420'}" id="banner">          
            <div class="common-banner-image common-banner-image-cover">
                <div class="common-banner-title">
                    <div class="bread-crumb hidden-sm hidden-xs">
                        <ul>
                            <li><a href="/partnerancasestudy/case-studies/" id="parter_case_rolls-royce" class="single-link">客户案例</a></li>
                            <li><span>&gt;</span></li>
                            <li><span class="single-link single-link-nohover">劳斯莱斯</span></li>
                        </ul>
                    </div>
                    <div class="video-detail">
                        <div class="case-study-layer">
                            <a href="http://www.rolls-roycemotorcars.com.cn/" id="case-study-rolls-roycewebsite" target="_blank" rel=“nofollow"><img src="//wacnppe.blob.core.chinacloudapi.cn/marketing-resource/media/images/casestudy/rolls-royce-80.png" class="casestudy-logo" data-rjs="2"/></a>
                            <h1>劳斯莱斯</h1>
                            <p>劳斯莱斯利用 Cortana 人工智能系统及 Azure IoT 套件远程数据分析，实现效能最大化。</p>
                        </div>
                         <p class="casestudy-info">
                            通过 Cortana 人工智能系统及 Azure IoT 套件提供的先进的数据分析服务及物联网管理平台和实时操作建议，节约了燃料预测维修需求，减少了代价高昂的停机检测和延误时间，从而减少库存成本，提高可用性，实现效能最大化，为客户带来安全高效的乘车体验。
                         </p> 
                        
                        <a href="#" class="video-play-button" id="case-study-video-player"></a>
                    </div>
                          
                    <div class="video-center">  
                        <div class="video-instance">                            
                            <video id="case-study-video" class="video-js vjs-tech responsive-size" preload="none" width="100%" height="100%"
                                   poster="" data-setup='{ "controls": false }'>
                                <source src="//wacnppe.blob.core.chinacloudapi.cn/marketing-resource/media/images/casestudy/Rolls-Royce_Chinese%20Subtitle.mp4" type='video/mp4'>
                            </video>
                            <a href="#" class="video-close" id="case-study-video-close"><i class="icon icon-close"></i></a>
                        </div>
                    </div>
                </div>
            </div>
        </div>
        <!-- End: Banner-->
    ]]></banner>
    <disqusComments>0</disqusComments>
    <metaCanonical></metaCanonical>
    <isHeader>0</isHeader>
    <pageTemplate></pageTemplate>
    <localize>0</localize>
    <localizePartial>0</localizePartial>
    <sitemapHide>0</sitemapHide>
    <headerText><![CDATA[]]></headerText>
    <forbidPublish>0</forbidPublish>
  </umbTextpage>
</localize>
