<?xml version="1.0" encoding="utf-8"?>
<localize>
  <umbTextpage id="18482" parentID="12022" level="3" writerID="106" creatorID="94" nodeType="1059" template="11" sortOrder="0" createDate="2013-05-05T16:51:50" updateDate="2018-06-07T10:23:53" nodeName="Overview" urlName="overview" writerName="content" creatorName="xunfan" path="-1,11978,12022,18482" isDoc="">
    <bodyText>
      <![CDATA[
	      <div class="main">
			<div class="banner_box">
				<div class="banner container">
					<div class="content">
						<h1>Azure Pricing</h1>
						<div class="banner-p">Flexible purchase and pricing options for a variety of cloud solutions</div>
						<div class="banner-b">
							<div class="icon_hook"><i class="icon icon-tick"></i>
								<span>Billed by actual usage</span>
							</div>
							<div class="icon_hook"><i class="icon icon-tick"></i>
								<span>Tiered billing</span>
							</div>
							<div class="icon_hook"><i class="icon icon-tick"></i>
								<span>Discount for preview services</span>
							</div>
						</div>
					</div>
				</div>
			</div>

			<div id="row2" class="container">
				<div class='title'>
					<h1>Explore pricing details of Azure products</h1>
					<div class="home-p">
						Azure as a global service, we use Coordinated Universal Time (UTC) to calculate the usage.
					</div>
					<a target="_blank" href="https://www.azure.cn/en-us/pricing/calculator/" class="calculator">
						<div class="calculator_btn">
							<i class='svg-icon-calculator-small'></i><span>Pricing calculator</span><i class="svg-icon-right"></i>
						</div>
					</a>
				</div>
				<div class="product" id="my-gallery-container">
					<div class='col-md-3 col-xs-none'>
						<div class='item' data-order="0">
							<dl>
								<dt><h2>AI</h2></dt>
								<dd>
									<dl class='pb0'>
										<dt><a href="/pricing/details/cognitive-services/" ><i class='svg-icon-azure-cognative-services'></i><span>Cognitive Services</span></a></dt>
										<dd class='leftline'><a href="/pricing/details/cognitive-services/" ><i class='svg-icon-azure-cognative-services-face'></i><span>Face API</span></a></dd>
										<dd class='leftline'><a href="/pricing/details/cognitive-services/" ><i class='svg-icon-azure-cognative-services-computer-vision'></i><span>Computer Vision API</span></a></dd>
										<dd class='leftline'><a href="/pricing/details/cognitive-services/" ><i class='svg-icon-azure-cognative-services-content-moderator'></i><span>Content Moderator API</span></a></dd>
										<dd class='leftline'><a href="/pricing/details/cognitive-services/" ><i class='svg-icon-azure-cognative-services-text-analytics'></i><span>Text Analytics API</span></a></dd>
									</dl>
								</dd>
							</dl>
						</div>
						<div class='item' data-order="4">
							<dl>
								<dt><h2>Management Tools</h2></dt>
								<dd><a href="/pricing/details/automation/" ><i class='svg-icon-automation'></i><span>Automation</span></a></dd>
								<dd><a href="/pricing/details/backup/" ><i class='svg-icon-azure-backup'></i><span>Backup</span></a></dd>
								<dd><a href="/pricing/details/site-recovery/" ><i class='svg-icon-azure-site-recovery'></i><span>Site Recovery</span></a></dd>
								<dd><a href="/pricing/details/scheduler/" ><i class='svg-icon-azure-scheduler'></i><span>Scheduler</span></a></dd>
								<dd><a href="/pricing/details/monitor/" ><i class='svg-icon-azure-monitor'></i><span>Azure Monitor</span></a></dd>
								<dd><a href="/pricing/details/traffic-manager/" ><i class='svg-icon-azure-traffic-manager'></i><span>Traffic Manager</span></a></dd>
								<dd><a href="/pricing/details/network-watcher/" ><i class='svg-icon-azure-network-watcher'></i><span>Network Watcher</span></a></dd>
								<dd><a href="/pricing/details/azure-policy/" ><i class='svg-icon-azure-services-policy'></i><span>Azure Policy</span></a></dd>
							</dl>
						</div>
						<div class='item' data-order="8">
							<dl>
								<dt><h2>Migration</h2></dt>
								<dd><a href="/pricing/details/site-recovery/" ><i class='svg-icon-azure-site-recovery'></i><span>Site Recovery</span></a></dd>
							</dl>
						</div>
						<div class='item pb0' data-order="12">
							<dl>
								<dt><h2>Databases</h2></dt>
								<dd><a href="/pricing/details/sql-database/" ><i class='svg-icon-sql-database'></i><span>SQL Database</span></a></dd>
								<dd><a href="/pricing/details/sql-data-warehouse/" ><i class='svg-icon-azure-SQL-DataWarehouse'></i><span>SQL Data Warehouse</span></a></dd>
								<dd><a href="/pricing/details/sql-server-stretch-database/" ><i class='svg-icon-stretch-database'></i><span>SQL Server Stretch Database</span></a></dd>
								<dd><a href="/pricing/details/cosmos-db/" ><i class='svg-icon-azure-cosmos'></i><span>Azure Cosmos DB</span></a></dd>
								<dd><a href="/pricing/details/redis-cache/" ><i class='svg-icon-redis'></i><span>Azure Cache for Redis</span></a></dd>
								<dd><a href="/pricing/details/mysql/" ><i class='svg-icon-mysql'></i><span>Azure Database for MySQL</span></a></dd>
								<dd><a href="/pricing/details/postgresql/" ><i class='svg-icon-azure-services-postgresql'></i><span>Azure Database for PostgreSQL</span></a></dd>
							</dl>
						</div>
					</div>
					<div class='col-md-3 col-xs-none'>
						<div class='item' data-order="1">
							<dl>
								<dt><h2>Security</h2></dt>
								<dd><a href="/pricing/details/key-vault/" ><i class='svg-icon-key-vault'></i><span>Key Vault</span></a></dd>
								<dd><a href="/pricing/details/active-directory/" ><i class='svg-icon-azure-active-directory'></i><span>Azure Active Directory</span></a></dd>
								<dd><a href="/pricing/details/application-gateway/" ><i class='svg-icon-azure-application-gateway'></i><span>Application Gateway</span></a></dd>
								<dd><a href="/pricing/details/vpn-gateway/" ><i class='svg-icon-vpn-gateway'></i><span>VPN Gateway</span></a></dd>
							</dl>
						</div>
						<div class='item' data-order="5">
							<dl>
								<dt><h2>Integration</h2></dt>
								<dd><a href="/pricing/details/service-bus/" ><i class='svg-icon-azure-service-bus'></i><span>Service Bus</span></a></dd>
								<dd><a href="/pricing/details/api-management/" ><i class='svg-icon-azure-API-management'></i><span>API Management</span></a></dd>
							</dl>
						</div>
						<div class='item' data-order="9">
							<dl>
								<dt><h2>Compute</h2></dt>
								<dd><a href="/pricing/details/virtual-machines/" ><i class='svg-icon-vmss'></i><span>Virtual Machines</span></a></dd>
								<dd><a href="/pricing/details/virtual-machine-scale-sets/" ><i class='svg-icon-vmss'></i><span>Virtual Machine Scale Sets</span></a></dd>
								<dd><a href="/pricing/details/app-service/" ><i class='svg-icon-azure-app-service'></i><span>App Service</span></a></dd>
								<dd><a href="/pricing/details/batch/" ><i class='svg-icon-batch'></i><span>Batch processing</span></a></dd>
								<dd><a href="/pricing/details/service-fabric/" ><i class='svg-icon-fabric'></i><span>Service Fabric</span></a></dd>
								<dd><a href="/pricing/details/cloud-services/" ><i class='svg-icon-azure-cloud-service'></i><span>Cloud Services</span></a></dd>
								<dd><a href="/pricing/details/azure-functions/" ><i class='svg-icon-azure-functions'></i><span>Azure Functions</span></a></dd>
							</dl>
						</div>
						<div class='item pb0' data-order="13">
							<dl>
								<dt><h2>Internet of Things</h2></dt>
								<dd><a href="/pricing/details/iot-hub/" ><i class='svg-icon-azure-IoT-hub'></i><span>Azure IoT Hub</span></a></dd>
								<dd><a href="/pricing/details/event-hubs/" ><i class='svg-icon-event-hubs'></i><span>Event Hubs</span></a></dd>
								<dd><a href="/pricing/details/stream-analytics/" ><i class='svg-icon-stream-analytics'></i><span>Stream Analytics</span></a></dd>
								<dd><a href="/pricing/details/logic-apps/" ><i class='svg-icon-azure-logic-apps'></i><span>Logic Apps</span></a></dd>
								<dd><a href="/pricing/details/notification-hubs/" ><i class='svg-icon-notification-hubs'></i><span>Notification Hubs</span></a></dd>
								<dd><a href="/pricing/details/cosmos-db/" ><i class='svg-icon-azure-cosmos'></i><span>Azure Cosmos DB</span></a></dd>
								<dd><a href="/pricing/details/api-management/" ><i class='svg-icon-azure-API-management'></i><span>API Management</span></a></dd>
							</dl>
						</div>
					</div>
					<div class='col-md-3 col-xs-none'>
						<div class='item' data-order="2">
							<dl>
								<dt><h2>Identity</h2></dt>
								<dd><a href="/pricing/details/active-directory/" ><i class='svg-icon-azure-active-directory'></i><span>Azure Active Directory</span></a></dd>
								<dd><a href="/pricing/details/multi-factor-authentication/" ><i class='svg-icon-multi-factor-authentication'></i><span>Multi-Factor Authentication</span></a></dd>
							</dl>
						</div>
						<div class='item' data-order="6">
							<dl>
								<dt><h2>Analysis</h2></dt>
								<dd><a href="/pricing/details/sql-data-warehouse/" ><i class='svg-icon-azure-SQL-DataWarehouse'></i><span>SQL Data Warehouse</span></a></dd>
								<dd><a href="/pricing/details/hdinsight/" ><i class='svg-icon-azure-HDInsight'></i><span>HDInsight</span></a></dd>
								<dd><a href="/pricing/details/stream-analytics/" ><i class='svg-icon-stream-analytics'></i><span>Stream Analytics</span></a></dd>
								<dd><a href="/pricing/details/power-bi-embedded/" ><i class='svg-icon-power-bi'></i><span>Power BI Embedded</span></a></dd>
								<dd><a href="/pricing/details/analysis-services/" ><i class='svg-icon-azure-analysis-service'></i><span>Azure Analysis Services</span></a></dd>
								<dd><a href="/pricing/details/event-hubs/" ><i class='svg-icon-event-hubs'></i><span>Event Hubs</span></a></dd>
							</dl>
						</div>
						<div class='item' data-order="10">
							<dl>
								<dt><h2>Networking</h2></dt>
								<dd><a href="/pricing/details/virtual-network/" ><i class='svg-icon-networking'></i><span>Virtual Network</span></a></dd>
								<dd><a href="/pricing/details/load-balancer/" ><i class='svg-icon-azure-load-balancer'></i><span>Load Balancer</span></a></dd>
								<dd><a href="/pricing/details/application-gateway/" ><i class='svg-icon-azure-application-gateway'></i><span>Application Gateway</span></a></dd>
								<dd><a href="/pricing/details/vpn-gateway/" ><i class='svg-icon-vpn-gateway'></i><span>VPN Gateway</span></a></dd>
								<dd><a href="/pricing/details/cdn/" ><i class='svg-icon-cdn'></i><span>Content Delivery Network</span></a></dd>
								<dd><a href="/pricing/details/traffic-manager/" ><i class='svg-icon-azure-traffic-manager'></i><span>Traffic Manager</span></a></dd>
								<dd><a href="/pricing/details/ccs/" ><i class='svg-icon-azure-cloud-connection-service'></i><span>Cloud Connection Service</span></a></dd>
								<dd><a href="/pricing/details/expressroute/" ><i class='svg-icon-azure-express-route'></i><span>ExpressRoute</span></a></dd>
								<dd><a href="/pricing/details/data-transfer/" ><i class='svg-icon-azure-small'></i><span>Data Transfer (Bandwidth)</span></a></dd>
								<dd><a href="/pricing/details/ip-addresses/" ><i class='svg-icon-azure-small'></i><span>IP Address</span></a></dd>
								<dd><a href="/pricing/details/network-watcher/" ><i class='svg-icon-azure-network-watcher'></i><span>Network Watcher</span></a></dd>
								<dd><a href="/pricing/details/dns/" ><i class='svg-icon-azure-dns'></i><span>Azure DNS</span></a></dd>
							</dl>
						</div>
						<div class='item pb0' data-order="14">
							<dl>
								<dt><h2>Mobile</h2></dt>
								<dd><a href="/pricing/details/app-service/" ><i class='svg-icon-azure-app-service'></i><span>App Service</span></a></dd>
								<dd><a href="/pricing/details/customer-engagement-fabric/" ><i class='svg-icon-customer-engagement-fabric'></i><span>Customer Engagement Fabric</span></a></dd>
							</dl>
						</div>
					</div>
					<div class='col-md-3 col-xs-none'>
						<div class='item' data-order="3">
							<dl>
								<dt><h2>Storage</h2></dt>
								<dd>
									<dl class='pb0'>
										<dt><a href="/pricing/details/storage/" ><i class='svg-icon-storage'></i><span>Storage</span></a></dt>
										<dd class='leftline'><a href="/pricing/details/storage/blobs/" ><i class='svg-icon-storage'></i><span>Block Blobs</span></a></dd>
										<dd class='leftline'><a href="/pricing/details/storage/page-blobs/" ><i class='svg-icon-storage'></i><span>Page blobs</span></a></dd>
										<dd class='leftline'><a href="/pricing/details/storage/managed-disks/" ><i class='svg-icon-storage'></i><span>Managed Disks</span></a></dd>
										<dd class='leftline'><a href="/pricing/details/storage/files/" ><i class='svg-icon-azure-storage-files'></i><span>Files</span></a></dd>
										<dd class='leftline'><a href="/pricing/details/storage/queues/" ><i class='svg-icon-storage'></i><span>Queues</span></a></dd>
										<dd class='leftline'><a href="/pricing/details/storage/tables/" ><i class='svg-icon-storage'></i><span>Tables</span></a></dd>
										<dd class='leftline'><a href="/pricing/details/storage/data-lake/" ><i class='svg-icon-azure-storage-data-lake'></i><span>Azure Data Lake Storage</span></a></dd>
									</dl>
								</dd>
								<dd><a href="/pricing/details/backup/" ><i class='svg-icon-back-up'></i><span>Backup</span></a></dd>
								<dd><a href="/pricing/details/site-recovery/" ><i class='svg-icon-azure-site-recovery'></i><span>Site Recovery</span></a></dd>
								<dd><a href="/pricing/details/storage-import-export/" ><i class='svg-icon-azure-small'></i><span>Import/Export</span></a></dd>
							</dl>
						</div>
						<div class='item' data-order="7">
							<dl>
								<dt><h2>Media</h2></dt>
								<dd><a href="/pricing/details/media-services/" ><i class='svg-icon-media-services'></i><span>Media Services</span></a></dd>
							</dl>
						</div>
						<div class='item' data-order="11">
							<dl>
								<dt><h2>Containers</h2></dt>
								<dd><a href="/pricing/details/app-service/" ><i class='svg-icon-azure-app-service'></i><span>App Service</span></a></dd>
								<dd><a href="/pricing/details/batch/" ><i class='svg-icon-batch'></i><span>Batch processing</span></a></dd>
								<dd><a href="/pricing/details/service-fabric/" ><i class='svg-icon-fabric'></i><span>Service Fabric</span></a></dd>
							</dl>
						</div>
						<div class='item pb0' data-order="15">
							<dl>
								<dt><h2>Web</h2></dt>
								<dd><a href="/pricing/details/app-service/" ><i class='svg-icon-azure-app-service'></i><span>App Service</span></a></dd>
								<dd><a href="/pricing/details/notification-hubs/" ><i class='svg-icon-notification-hubs'></i><span>Notification Hubs</span></a></dd>
								<dd><a href="/pricing/details/api-management/" ><i class='svg-icon-azure-API-management'></i><span>API Management</span></a></dd>
								<dd><a href="/pricing/details/cdn/" ><i class='svg-icon-cdn'></i><span>Content Delivery Network</span></a></dd>
								<dd><a href="/pricing/details/customer-engagement-fabric/" ><i class='svg-icon-customer-engagement-fabric'></i><span>Customer Engagement Fabric</span></a></dd>
							</dl>
						</div>
					</div>
					
					<div class='col-md-block col-xs-6 pr24'>
						<div class='item' data-order="0">
							<dl>
								<dt><h2>AI</h2></dt>
								<dd>
									<dl class='pb0'>
										<dt><a href="/pricing/details/cognitive-services/" ><i class='svg-icon-azure-cognative-services'></i><span>Cognitive Services</span></a></dt>
										<dd class='leftline'><a href="/pricing/details/cognitive-services/" ><i class='svg-icon-azure-cognative-services-face'></i><span>Face API</span></a></dd>
										<dd class='leftline'><a href="/pricing/details/cognitive-services/" ><i class='svg-icon-azure-cognative-services-computer-vision'></i><span>Computer Vision API</span></a></dd>
										<dd class='leftline'><a href="/pricing/details/cognitive-services/" ><i class='svg-icon-azure-cognative-services-content-moderator'></i><span>Content Moderator API</span></a></dd>
										<dd class='leftline'><a href="/pricing/details/cognitive-services/" ><i class='svg-icon-azure-cognative-services-text-analytics'></i><span>Text Analytics API</span></a></dd>
									</dl>
								</dd>
							</dl>
						</div>
						<div class='item' data-order="2">
							<dl>
								<dt><h2>Identity</h2></dt>
								<dd><a href="/pricing/details/active-directory/" ><i class='svg-icon-azure-active-directory'></i><span>Azure Active Directory</span></a></dd>
								<dd><a href="/pricing/details/multi-factor-authentication/" ><i class='svg-icon-multi-factor-authentication'></i><span>Multi-Factor Authentication</span></a></dd>
							</dl>
						</div>
						<div class='item' data-order="6">
							<dl>
								<dt><h2>Analysis</h2></dt>
								<dd><a href="/pricing/details/sql-data-warehouse/" ><i class='svg-icon-azure-SQL-DataWarehouse'></i><span>SQL Data Warehouse</span></a></dd>
								<dd><a href="/pricing/details/hdinsight/" ><i class='svg-icon-azure-HDInsight'></i><span>HDInsight</span></a></dd>
								<dd><a href="/pricing/details/stream-analytics/" ><i class='svg-icon-stream-analytics'></i><span>Stream Analytics</span></a></dd>
								<dd><a href="/pricing/details/power-bi-embedded/" ><i class='svg-icon-power-bi'></i><span>Power BI Embedded</span></a></dd>
								<dd><a href="/pricing/details/analysis-services/" ><i class='svg-icon-azure-analysis-service'></i><span>Azure Analysis Services</span></a></dd>
								<dd><a href="/pricing/details/event-hubs/" ><i class='svg-icon-event-hubs'></i><span>Event Hubs</span></a></dd>
							</dl>
						</div>
						<div class='item' data-order="4">
							<dl>
								<dt><h2>Management Tools</h2></dt>
								<dd><a href="/pricing/details/automation/" ><i class='svg-icon-automation'></i><span>Automation</span></a></dd>
								<dd><a href="/pricing/details/backup/" ><i class='svg-icon-azure-backup'></i><span>Backup</span></a></dd>
								<dd><a href="/pricing/details/site-recovery/" ><i class='svg-icon-azure-site-recovery'></i><span>Site Recovery</span></a></dd>
								<dd><a href="/pricing/details/scheduler/" ><i class='svg-icon-azure-scheduler'></i><span>Scheduler</span></a></dd>
								<dd><a href="/pricing/details/monitor/" ><i class='svg-icon-azure-monitor'></i><span>Azure Monitor</span></a></dd>
								<dd><a href="/pricing/details/traffic-manager/" ><i class='svg-icon-azure-traffic-manager'></i><span>Traffic Manager</span></a></dd>
								<dd><a href="/pricing/details/network-watcher/" ><i class='svg-icon-azure-network-watcher'></i><span>Network Watcher</span></a></dd>
								<dd><a href="/pricing/details/azure-policy/" ><i class='svg-icon-azure-services-policy'></i><span>Azure Policy</span></a></dd>
							</dl>
						</div>
						<div class='item' data-order="11">
							<dl>
								<dt><h2>Containers</h2></dt>
								<dd><a href="/pricing/details/app-service/" ><i class='svg-icon-azure-app-service'></i><span>App Service</span></a></dd>
								<dd><a href="/pricing/details/batch/" ><i class='svg-icon-batch'></i><span>Batch processing</span></a></dd>
								<dd><a href="/pricing/details/service-fabric/" ><i class='svg-icon-fabric'></i><span>Service Fabric</span></a></dd>
							</dl>
						</div>
						<div class='item' data-order="7">
							<dl>
								<dt><h2>Media</h2></dt>
								<dd><a href="/pricing/details/media-services/" ><i class='svg-icon-media-services'></i><span>Media Services</span></a></dd>
							</dl>
						</div>
						<div class='item' data-order="8">
							<dl>
								<dt><h2>Migration</h2></dt>
								<dd><a href="/pricing/details/site-recovery/" ><i class='svg-icon-azure-site-recovery'></i><span>Site Recovery</span></a></dd>
							</dl>
						</div>
						<div class='item' data-order="12">
							<dl>
								<dt><h2>Databases</h2></dt>
								<dd><a href="/pricing/details/sql-database/" ><i class='svg-icon-sql-database'></i><span>SQL Database</span></a></dd>
								<dd><a href="/pricing/details/sql-data-warehouse/" ><i class='svg-icon-azure-SQL-DataWarehouse'></i><span>SQL Data Warehouse</span></a></dd>
								<dd><a href="/pricing/details/sql-server-stretch-database/" ><i class='svg-icon-stretch-database'></i><span>SQL Server Stretch Database</span></a></dd>
								<dd><a href="/pricing/details/cosmos-db/" ><i class='svg-icon-azure-cosmos'></i><span>Azure Cosmos DB</span></a></dd>
								<dd><a href="/pricing/details/redis-cache/" ><i class='svg-icon-redis'></i><span>Azure Cache for Redis</span></a></dd>
								<dd><a href="/pricing/details/mysql/" ><i class='svg-icon-mysql'></i><span>Azure Database for MySQL</span></a></dd>
								<dd><a href="/pricing/details/postgresql/" ><i class='svg-icon-azure-services-postgresql'></i><span>Azure Database for PostgreSQL</span></a></dd>
							</dl>
						</div>
						<div class='item' data-order="15">
							<dl>
								<dt><h2>Web</h2></dt>
								<dd><a href="/pricing/details/app-service/" ><i class='svg-icon-azure-app-service'></i><span>App Service</span></a></dd>
								<dd><a href="/pricing/details/notification-hubs/" ><i class='svg-icon-notification-hubs'></i><span>Notification Hubs</span></a></dd>
								<dd><a href="/pricing/details/api-management/" ><i class='svg-icon-azure-API-management'></i><span>API Management</span></a></dd>
								<dd><a href="/pricing/details/cdn/" ><i class='svg-icon-cdn'></i><span>Content Delivery Network</span></a></dd>
								<dd><a href="/pricing/details/customer-engagement-fabric/" ><i class='svg-icon-customer-engagement-fabric'></i><span>Customer Engagement Fabric</span></a></dd>
							</dl>
						</div>
						<div class='item col-sm-none pb0' data-order="14">
							<dl>
								<dt><h2>Mobile</h2></dt>
								<dd><a href="/pricing/details/app-service/" ><i class='svg-icon-azure-app-service'></i><span>App Service</span></a></dd>
								<dd><a href="/pricing/details/customer-engagement-fabric/" ><i class='svg-icon-customer-engagement-fabric'></i><span>Customer Engagement Fabric</span></a></dd>
							</dl>
						</div>
					</div>
					<div class='col-md-block col-xs-6'>
						<div class='item' data-order="1">
							<dl>
								<dt><h2>Security</h2></dt>
								<dd><a href="/pricing/details/key-vault/" ><i class='svg-icon-key-vault'></i><span>Key Vault</span></a></dd>
								<dd><a href="/pricing/details/active-directory/" ><i class='svg-icon-azure-active-directory'></i><span>Azure Active Directory</span></a></dd>
								<dd><a href="/pricing/details/application-gateway/" ><i class='svg-icon-azure-application-gateway'></i><span>Application Gateway</span></a></dd>
								<dd><a href="/pricing/details/vpn-gateway/" ><i class='svg-icon-vpn-gateway'></i><span>VPN Gateway</span></a></dd>
							</dl>
						</div>
						<div class='item' data-order="3">
							<dl>
								<dt><h2>Storage</h2></dt>
								<dd>
									<dl class='pb0'>
										<dt><a href="/pricing/details/storage/" ><i class='svg-icon-storage'></i><span>Storage</span></a></dt>
										<dd class='leftline'><a href="/pricing/details/storage/blobs/" ><i class='svg-icon-storage'></i><span>Block Blobs</span></a></dd>
										<dd class='leftline'><a href="/pricing/details/storage/page-blobs/" ><i class='svg-icon-storage'></i><span>Page blobs</span></a></dd>
										<dd class='leftline'><a href="/pricing/details/storage/managed-disks/" ><i class='svg-icon-storage'></i><span>Managed Disks</span></a></dd>
										<dd class='leftline'><a href="/pricing/details/storage/files/" ><i class='svg-icon-azure-storage-files'></i><span>Files</span></a></dd>
										<dd class='leftline'><a href="/pricing/details/storage/queues/" ><i class='svg-icon-storage'></i><span>Queues</span></a></dd>
										<dd class='leftline'><a href="/pricing/details/storage/tables/" ><i class='svg-icon-storage'></i><span>Tables</span></a></dd>
										<dd class='leftline'><a href="/pricing/details/storage/data-lake/" ><i class='svg-icon-azure-storage-data-lake'></i><span>Azure Data Lake Storage</span></a></dd>
									</dl>
								</dd>
								<dd><a href="/pricing/details/backup/" ><i class='svg-icon-azure-backup'></i><span>Backup</span></a></dd>
								<dd><a href="/pricing/details/site-recovery/" ><i class='svg-icon-azure-site-recovery'></i><span>Site Recovery</span></a></dd>
								<dd><a href="/pricing/details/storage-import-export/" ><i class='svg-icon-azure-small'></i><span>Import/Export</span></a></dd>
							</dl>
						</div>
						<div class='item' data-order="5">
							<dl>
								<dt><h2>Integration</h2></dt>
								<dd><a href="/pricing/details/service-bus/" ><i class='svg-icon-azure-service-bus'></i><span>Service Bus</span></a></dd>
								<dd><a href="/pricing/details/api-management/" ><i class='svg-icon-azure-API-management'></i><span>API Management</span></a></dd>
							</dl>
						</div>
						<div class='item' data-order="9">
							<dl>
								<dt><h2>Compute</h2></dt>
								<dd><a href="/pricing/details/virtual-machines/" ><i class='svg-icon-vmss'></i><span>Virtual Machines</span></a></dd>
								<dd><a href="/pricing/details/virtual-machine-scale-sets/" ><i class='svg-icon-vmss'></i><span>Virtual Machine Scale Sets</span></a></dd>
								<dd><a href="/pricing/details/app-service/" ><i class='svg-icon-azure-app-service'></i><span>App Service</span></a></dd>
								<dd><a href="/pricing/details/batch/" ><i class='svg-icon-batch'></i><span>Batch processing</span></a></dd>
								<dd><a href="/pricing/details/service-fabric/" ><i class='svg-icon-fabric'></i><span>Service Fabric</span></a></dd>
								<dd><a href="/pricing/details/cloud-services/" ><i class='svg-icon-azure-cloud-service'></i><span>Cloud Services</span></a></dd>
								<dd><a href="/pricing/details/azure-functions/" ><i class='svg-icon-azure-functions'></i><span>Azure Functions</span></a></dd>
							</dl>
						</div>
						<div class='item' data-order="10">
							<dl>
								<dt><h2>Networking</h2></dt>
								<dd><a href="/pricing/details/virtual-network/" ><i class='svg-icon-networking'></i><span>Virtual Network</span></a></dd>
								<dd><a href="/pricing/details/load-balancer/" ><i class='svg-icon-azure-load-balancer'></i><span>Load Balancer</span></a></dd>
								<dd><a href="/pricing/details/application-gateway/" ><i class='svg-icon-azure-application-gateway'></i><span>Application Gateway</span></a></dd>
								<dd><a href="/pricing/details/vpn-gateway/" ><i class='svg-icon-vpn-gateway'></i><span>VPN Gateway</span></a></dd>
								<dd><a href="/pricing/details/cdn/" ><i class='svg-icon-cdn'></i><span>Content Delivery Network</span></a></dd>
								<dd><a href="/pricing/details/traffic-manager/" ><i class='svg-icon-azure-traffic-manager'></i><span>Traffic Manager</span></a></dd>
								<dd><a href="/pricing/details/ccs/" ><i class='svg-icon-azure-cloud-connection-service'></i><span>Cloud Connection Service</span></a></dd>
								<dd><a href="/pricing/details/expressroute/" ><i class='svg-icon-azure-express-route'></i><span>ExpressRoute</span></a></dd>
								<dd><a href="/pricing/details/data-transfer/" ><i class='svg-icon-azure-small'></i><span>Data Transfer (Bandwidth)</span></a></dd>
								<dd><a href="/pricing/details/ip-addresses/" ><i class='svg-icon-azure-small'></i><span>IP Address</span></a></dd>
								<dd><a href="/pricing/details/network-watcher/" ><i class='svg-icon-azure-network-watcher'></i><span>Network Watcher</span></a></dd>
							</dl>
						</div>
						<div class='item' data-order="13">
							<dl>
								<dt><h2>Internet of Things</h2></dt>
								<dd><a href="/pricing/details/iot-hub/" ><i class='svg-icon-azure-IoT-hub'></i><span>Azure IoT Hub</span></a></dd>
								<dd><a href="/pricing/details/event-hubs/" ><i class='svg-icon-event-hubs'></i><span>Event Hubs</span></a></dd>
								<dd><a href="/pricing/details/stream-analytics/" ><i class='svg-icon-stream-analytics'></i><span>Stream Analytics</span></a></dd>
								<dd><a href="/pricing/details/logic-apps/" ><i class='svg-icon-azure-logic-apps'></i><span>Logic Apps</span></a></dd>
								<dd><a href="/pricing/details/notification-hubs/" ><i class='svg-icon-notification-hubs'></i><span>Notification Hubs</span></a></dd>
								<dd><a href="/pricing/details/cosmos-db/" ><i class='svg-icon-azure-cosmos'></i><span>Azure Cosmos DB</span></a></dd>
								<dd><a href="/pricing/details/api-management/" ><i class='svg-icon-azure-API-management'></i><span>API Management</span></a></dd>
							</dl>
						</div>
						<div class='item col-sm-block pb0' data-order="14">
							<dl>
								<dt><h2>Mobile</h2></dt>
								<dd><a href="/pricing/details/app-service/" ><i class='svg-icon-azure-app-service'></i><span>App Service</span></a></dd>
								<!-- <dd><a href="/pricing/details/customer-engagement-fabric/" ><i class='svg-icon-customer-engagement-fabric'></i><span>Customer Engagement Fabric</span></a></dd> -->
							</dl>
						</div>
					</div>

				</div>
			</div>
			<div id='row5'>
				<div class="container">
					<h1>Resources</h1>
					<div class='content'>
						<div class='col-sm-1-5 col-md-1-5 col-lg-1-5 item calculator'>
							<i class='svg-icon-calculator left'></i>
							<div class='right'>
								<p><a target="_blank" href="https://www.azure.cn/en-us/pricing/calculator/" title="Calculator">Calculator</a></p>
								<p>Estimate your monthly costs for Azure services</p>
							</div>
						</div>
						<div class='col-sm-1-5 col-md-1-5 col-lg-1-5 item'>
							<i class='svg-icon-FAQ left'></i>
							<div class='right'>
								<p><a target="_blank" href="https://www.azure.cn/en-us/support/faq/#billingAndSubscription" title="Pricing FAQ">Pricing FAQ</a></p>
								<p>Review Azure pricing frequently asked questions</p>
							</div>
						</div>
						<div class='col-sm-1-5 col-md-1-5 col-lg-1-5 item'>
							<i class='svg-icon-sla left'></i>
							<div class='right'>
								<p><a target="_blank" href="https://www.azure.cn/en-us/support/legal/sla/" title="SLAs">SLAs</a></p>
								<p>Review Service Level Agreements of Azure services</p>
							</div>
						</div>
						<div class='col-sm-1-5 col-md-1-5 col-lg-1-5 item support-plan-height'>
							<i class='svg-icon-support-plan left'></i>
							<div class='right'>
								<p><a target="_blank" href="https://www.azure.cn/en-us/support/plans/" title="Support Plan">Support Plan</a></p>
								<p>Check out Azure support plans</p>
							</div>
						</div>
						<div class='col-sm-1-5 col-md-1-5 col-lg-1-5 item'>
							<i class='svg-icon-billing-doc left'></i>
							<div class='right'>
								<p><a target="_blank" href="https://docs.azure.cn/en-us/billing/" title="Billing Documentation">Billing Documentation</a></p>
								<p>Learn more about Azure billing</p>
							</div>
						</div>
					</div>
				</div>
			</div>
		</div>
	  ]]>
	</bodyText>
    <umbracoNaviHide>0</umbracoNaviHide>
    <pageTitle>Pricing Overview - Azure Cloud Computing</pageTitle>
    <metaKeywords>Azure, Fixed Price, Pricing, Pricing Calculator</metaKeywords>
    <metaDescription><![CDATA[After April 1, 2016, Azure product prices will undergo a complete price adjustment, with both excellent price offers and excellent service. A 1RMB Trial will get you ￥1,500 of service credits. Become an Azure Pay-in-Advance client and enjoy a 99.99% Service Level Agreement. You can rapidly deploy infrastructure and services to fully meet all of your enterprise needs, assisting you in reducing operational costs and allowing you to concentrate on your core business. ]]></metaDescription>
    <linkid>pricing-overview</linkid>
    <urlDisplayName>Azure Pricing Overview</urlDisplayName>
    <headerExpose></headerExpose>
    <footerExpose></footerExpose>
    <disqusComments>0</disqusComments>
    <metaCanonical></metaCanonical>
    <isHeader>0</isHeader>
    <pageTemplate></pageTemplate>
    <localize>0</localize>
    <localizePartial>0</localizePartial>
    <sitemapHide>1</sitemapHide>
    <headerText><![CDATA[]]></headerText>
    <forbidPublish>0</forbidPublish>
  </umbTextpage>
</localize>
