<?xml version="1.0" encoding="UTF-8"?>
<localize>
  <TextpageLeftNav template="5" createDate="2019-08-28T07:49:24" updateDate="2019-08-28T10:15:59" urlName="information-protection" writerName="content" creatorName="content">
    <bodyText>
      <![CDATA[
            <tags ms.service="information-protection" ms.date="09/30/2015" wacn.date="11/27/2015"></tags>
            <!-- BEGIN: Product-Detail-TopBanner -->
            <div class="common-banner col-top-banner" data-config="{'backgroundColor':'#e3f4ff', 'backgroundImage':'//wacnppe.blob.core.chinacloudapi.cn/marketing-resource/css/information-protection_banner.png','imageHeight':'auto'}">
                <div class="common-banner-image">
                    <div class="common-banner-title">
                        <img src="//wacnppe.blob.core.chinacloudapi.cn/marketing-resource/css/information-protection_icon@2x.svg" />
                        <h2>Azure Information Protection<span>Azure Information Protection</span></h2>
                        <h4>Better protect your sensitive information-anytime, anywhere</h4>
                        <em><a href="/pricing/1rmb-trial/" id="home_mysql_trial">Apply for 1RMB Trial<i class="icon icon-arrow-right-thin"></i></a></em> <a href="/pricing/pia/" id="home_information-protection_pia">Buy Now<i class="icon icon-arrow-right-thin"></i></a>
                    </div>
                </div>
            </div>
            <!-- END: Product-Detail-TopBanner -->
            <div class="pricing-page-section">
                <p>No upfront cost, No termination fees, Pay only for what you need</p>
            </div>
            <div class="pricing-page-section">
                <table cellpadding="0" cellspacing="0" width="100%">
                    <tbody>
                        <tr>
                            <th align="left"><strong>FEATURE</strong></th>
                            <th align="left">AZURE INFORMATION PROTECTION FOR OFFICE 365</th>
                        </tr>
                        <tr>
                            <td align="left">Azure Information Protection content consumption by using work or school accounts from AIP policy-aware apps and services</td>
                            <td align="left"><i class="icon icon-tick"></i></td>
                        </tr>
                        <tr>
                            <td align="left">Protection for Microsoft Exchange Online</td>
                            <td align="left"><i class="icon icon-tick"></i></td>
                        </tr>
                        <tr>
                            <td align="left">Bring Your Own Key (BYOK) for customer-managed key provisioning life cycle<sup>1</sup></td>
                            <td align="left"><i class="icon icon-tick"></i></td>
                        </tr>
                        <tr>
                            <td align="left">Custom templates, including departmental templates</td>
                            <td align="left"><i class="icon icon-tick"></i></td>
                        </tr>
                        <tr>
                            <td align="left">Azure Information Protection software developer kit for protection for all platforms – Windows, Windows Mobile, iOS, Mac OSX, and Android</td>
                            <td align="left"><i class="icon icon-tick"></i></td>
                        </tr>
                        <tr>
                            <td align="left">Protection for non-Microsoft Office file formats, including PTXT, PJPG, and PFILE (generic protection)</td>
                            <td align="left"><i class="icon icon-tick"></i></td>
                        </tr>
                        <tr>
                            <td align="left">Azure Information Protection content creation by using work or school accounts</td>
                            <td align="left"><i class="icon icon-tick"></i></td>
                        </tr>
                        <tr>
                            <td align="left">Office 365 Message Encryption</td>
                            <td align="left"><i class="icon icon-tick"></i></td>
                        </tr>
                        <tr>
                            <td align="left">Administrative control<sup>2</sup></td>
                            <td align="left"><i class="icon icon-tick"></i></td>
                        </tr>
                        <tr>
                            <td align="left">Sharing of protected emails to users in the commercial cloud </td>
                            <td align="left"><i class="icon icon-tick"></i></td>
                        </tr>
                    </tbody>
                </table>
                <div class="tags-date">
                    <div class="ms-date"><sup>1</sup> Azure subscription required to use configured key for Bring Your Own Key (BYOK).</div><br>
                    <div class="ms-date"><sup>2</sup> Includes activating/deactivating the service, onboarding controls for a phased deployment, usage logging, super user capability for eDiscovery and data recovery, bulk protect/unprotect of files.</div>
                </div>

                <h2>Azure Information Protection for Office 365</h2>
                <p>Azure Information Protection is included in the Office 365 Enterprise E3 and above plans.</p>
            </div>

            <div class="pricing-page-section">
                <div class="more-detail">
                    <h2>FAQs</h2>
                    <em>Expand All</em>

                    <h3>Consuming protected content – opening, viewing and modifying protected files</h3>
                    <ul>
                        <li>
                            <i class="icon icon-plus"></i>
                            <div>
                                <a id="home_information-protection_faq_Does-the-user-need-a-license-in-order-to-be-able-to-open-and-view-the-file" aria-label="A user wants to open and view a document that’s been protected by Azure Information Protection. Does the user need a license in order to be able to open and view the file?">A user wants to open and view a document that’s been protected by Azure Information Protection. Does the user need a license in order to be able to open and view the file?</a>
                                <section>
                                     <p>No. The worker doesn't need an Azure Information Protection license to open and view a file that’s been labeled and/or protected.</p>
                                </section>
                            </div>
                        </li>
                    </ul>
                </div>
            </div>

            <div class="pricing-page-section">
                <h2>Support &amp; SLA</h2>
                <p>If you have any questions or need help, please visit <a href="https://support.azure.cn/support/contact" id="information-protection-contact-page" aria-label="information-protection-contact-page" target="_blank">Azure Support</a> and select self-help service or any other method to contact us for support.</p>
                <p>As a free service, Azure Information Protection does not offer a financially-backed service level agreement. To learn more about the details of our Service Level Agreement, please visit the <a href="https://www.azure.cn/support/legal/sla">Service Level Agreements</a> page.</p>
            </div>

            <!-- BEGIN: TAB-CONTROL -->
            <!-- END: TAB-CONTROL -->
            <!--BEGIN: Support and service code chunk-->
            <?UMBRACO_MACRO chunkpath="production" chunkname="production-bottom-banner" macroAlias="blankCodeChunk" />                                                                        
            <!--END: Support and service code chunk-->                                                                                
    ]]>
    </bodyText>
    <pageTitle>Pricing – Information Protection - Azure Cloud Computing</pageTitle>
    <sitemapHide>0</sitemapHide>
    <linkid>Azure Information Protection</linkid>
    <metaKeywords>Azure, cloud service, Azure Information Protection</metaKeywords>
    <metaDescription><![CDATA[Explore pricing for Azure Information Protection.]]></metaDescription>
    <urlDisplayName>Azure Information Protection</urlDisplayName>
  </TextpageLeftNav>
</localize>
