<?xml version="1.0" encoding="UTF-8"?>
<localize><Chunk id="18754" parentID="18751" level="6" writerID="52" creatorID="94" nodeType="9257" template="0" sortOrder="3" createDate="2013-07-11T10:06:01" updateDate="2014-08-18T11:04:41" nodeName="Slide1" urlName="slide1" writerName="uRest" creatorName="xunfan" path="-1,11978,13607,16345,18617,18751,18754" isDoc=""><hideAll>0</hideAll><localize>1</localize><localizePartial>0</localizePartial><bodyText><![CDATA[<div style="background-image: url('/media/slides/mobile/bolt.png');">
<h2>移动服务</h2>
<h1>只需几秒即可保存和<strong>查询数据</strong>。</h1>
<pre><code>mobileService.getTable("Todo")<br />.insert({todo:"save data to the cloud"});</code></pre>
</div>]]></bodyText></Chunk></localize>