<?xml version="1.0" encoding="UTF-8"?>
<localize><umbTextpage id="19317" parentID="18484" level="5" writerID="52" creatorID="94" nodeType="1059" template="1136" sortOrder="5" createDate="2013-07-26T11:55:03" updateDate="2014-08-18T11:07:23" nodeName="July" urlName="july" writerName="uRest" creatorName="xunfan" path="-1,11978,12085,18483,18484,19317" isDoc=""><bodyText><![CDATA[<div style="padding-bottom: 60px; margin-top: 40px; margin-left: 25px; margin-right: 18px;">
<h1>Windows Azure<br />2013年7月时事通讯</h1>
<h2>公告</h2>
<h3>微软云加速器二期初创企业展示日在京举行(2013年7月7日)</h3>
<p>2013年7月7日，北京，微软宣布联合了BizSpark社区项目、加速器和Seed Fund种子资金的“Microsoft Ventures”（微软创投）正式进入中国。活动当天，恰逢一周年生日的微软云加速器还举办了二期创业团队展示日活动，同时宣布加速器三期正式启动以及当期入驻的创业团队名单。微软全球资深副总裁、微软亚太研发集团主席张亚勤博士、微软亚太研发集团首席运营官申元庆、Microsoft Ventures（微软创投）大中华区负责人林为千、微软云加速器前三期学员，以及数十位云加速器导师、微软合作伙伴、风险投资代表共同出席了此次活动。</p>
<p>刚刚被中关村科技园区管理委员会授予“创新型孵化器”称号的微软云加速器，其二期项目于2012年12月20日启动，通过6个月的加速成长，初创企业基于微软领先的技术平台，均推出了各具特色的产品与服务。数岩科技（厦门）、济南天宝信息科技、北京易动纷享科技、广西慧云信息科技、北京保益互动科技等多家由具有深厚行业积累和经验的创业者成立的初创企业，均推出了具有全球市场竞争力的产品与创新服务。</p>
<p>微软亚太研发集团主席张亚勤表示：“云正在重塑全球的技术和商业格局。刚刚在中国宣布的Windows Azure公众预览，对渴望抓住颠覆式创新机遇的创业者而言，意义非凡。很高兴看到在云加速器里，涌现出的这些‘小而美、快而精’的初创企业，能与同样处于重大转型阶段的微软，共同构建中国的云生态系统，一起把握命运、定义未来。”</p>
<p><a id="_know-more-color" href="http://www.microsoft.com/china/ard/news/news_20130707.aspx" class="_know-more-link">了解更多</a></p>
<h3>中国科大-微软软件工程中心成立(2013年7月5日)</h3>
<p>2013年7月5日，中国科学技术大学校长侯建国院士与微软公司全球资深副总裁，微软亚太研发集团主席张亚勤博士共同宣布，“中国科大-微软软件工程中心”正式成立。这是继5月22日，微软公司CEO史蒂夫∙鲍尔默正式宣布Windows Azure公共预览版在中国正式面世，微软公有云正式落地中国后，又一个具有里程碑意义的活动。这坚定地表明了微软对于中国市场的承诺——不但要把具有全球领先水平的云服务带到中国，同时愿意为中国本地云计算领域的科研提升、人才培养贡献一份力量。</p>
<p>签约揭牌仪式由中国科学技术大学副校长陈晓剑主持，中国科学技术大学信息科学技术学院院长李卫平，计算机学院、少年班学院、数学学院相关负责人，微软亚太研发集团研发总监黄海涛共同出席了中心签约揭牌仪式。</p>
<p>在活动前，张亚勤博士一行拜会了合肥市政府领导，分享了微软在云计算方面的最新战略，结合智慧城市的建设，云计算的发展和推动本地创新合作的话题，双方进行了深入地沟通与交流。</p>
<p>微软-中国科大软件工程中心是一个以云计算为主要方向，以人才培养、成果转换、产业创新、支撑服务为主要目标的研究中心， 由中国科技大学先进技术研究院负责日常管理运行。在这个中心里，中国科大与微软强强联合——依托中国科大的人才和基础科研优势，以及微软在云计算方面的技术和市场优势，实现双方的优势资源互补，激发出更多的创新活力，建设国内云计算与云服务的排头兵。该中心致力于培养更多云计算、数据处理、计算机和网络通信领域的优秀人才，从而推动科技和产业创新，同时向安徽省乃至全国提供先进的云计算和大数据服务。</p>
<p><a id="_know-more-color" href="http://www.microsoft.com/china/ard/news/news_20130705.aspx" class="_know-more-link">了解更多</a></p>
</div>]]></bodyText><umbracoNaviHide>0</umbracoNaviHide><pageTitle>Windows Azure 社区：最新公告</pageTitle><metaKeywords>Newsletter</metaKeywords><metaDescription><![CDATA[]]></metaDescription><linkid>newsletter-2013-july</linkid><urlDisplayName>七月</urlDisplayName><headerExpose></headerExpose><footerExpose></footerExpose><disqusComments>0</disqusComments><metaCanonical></metaCanonical><isHeader>0</isHeader><pageTemplate></pageTemplate><localize>0</localize><localizePartial>0</localizePartial><sitemapHide>0</sitemapHide><headerText>
  <![CDATA[<div class="_banner-general" style="height: 100px;">
<h1 class="_banner-h1"><span class="en">Windows Azure</span> 每月公告</h1>
<style>
  .backtowhat:hover{color:white !important;}
</style>
<a href="/what-is-new" class="backtowhat" style="color:#DDDDDD;font-size:16px;">返回最新公告<img src="//wacndevelop.blob.core.chinacloudapi.cn/marketing-resource/css/img/arrowright.png" style="width:28px;height:28px;margin:0px;display:inline-block;line-height:16px;vertical-align:middle;"></a>
</div>]]></headerText></umbTextpage></localize>