<?xml version="1.0" encoding="UTF-8"?>
<localize><umbTextpage id="18784" parentID="17371" level="4" writerID="52" creatorID="94" nodeType="1059" template="1052" sortOrder="9" createDate="2013-07-11T10:20:33" updateDate="2014-08-18T11:07:49" nodeName="app services" urlName="app-services" writerName="uRest" creatorName="xunfan" path="-1,11978,13431,17371,18784" isDoc=""><bodyText><![CDATA[<h1 id="menu-dotnet-appservices">应用服务</h1>
<h2>身份验证</h2>
<h3 class="feature"><span>功能指南：</span><a href="/zh-cn/develop/net/how-to-guides/access-control/">Access Control</a></h3>
<p>Access Control 是一项 Windows Azure 服务，可通过该服务轻松验证需要访问您的 Web 应用程序和服务的用户的身份，而不必在代码中添加复杂的身份验证逻辑因素。该服务还提供与 Windows Identity Foundation (WIF) 的集成，支持常用 Web 身份提供程序（包括 Windows Live ID、Google、Yahoo 和 Facebook），并且支持 ADFS 2.0。</p>
<h3 class="feature"><span>功能指南：</span><a href="/zh-cn/develop/net/fundamentals/identity/">Windows Azure 标识</a></h3>
<p>了解使用 Windows Server Active Directory 域服务 (AD)、Windows Azure Active Directory 和 Windows Azure Active Directory Access Control 在 Windows Azure 中管理身份的选项。</p>
<h3 class="tutorial"><span>教程：</span><a href="http://go.microsoft.com/fwlink/p/?LinkId=290964">使用 Windows Azure AD 将登录名添加到 Web 应用程序中</a></h3>
<p>了解如何构建使用 Windows Azure AD 实现单一登录的 Web 应用程序。</p>
<h3 class="tutorial"><span>教程：</span><a href="http://go.microsoft.com/fwlink/p/?LinkId=290970">利用 Windows Azure AD 开发多租户 Web 应用程序</a></h3>
<p>了解如何构建可供具有 Windows Azure AD 的组织使用的 Web 应用程序。</p>
<h3 class="tutorial"><span>教程：</span><a href="http://go.microsoft.com/fwlink/p/?LinkId=290969">使用 Graph API 查询 Windows Azure AD</a></h3>
<p>了解如何构建使用 Graph API 查询目录实体的 Web 应用程序。</p>
<h2>Caching </h2>
<h3 class="feature"><span>功能指南：</span><a href="/zh-cn/develop/net/how-to-guides/cache/">Caching</a></h3>
<p>Caching 服务通过暂时存储来自其他后端源的信息提高性能，并且可以减少云计算中与数据库事务相关的成本。</p>
<h2>电子邮件和音频</h2>
<!--<h3 class="feature"><span>功能指南：</span><a href="/zh-cn/develop/net/how-to-guides/sendgrid-email-service/">SendGrid 电子邮件服务</a></h3>
<p>Windows Azure 应用程序可以使用 SendGrid 来包括电子邮件功能。SendGrid 提供了可靠的电子邮件传递服务、实时分析和灵活的 API，使用户能够轻松地将服务合并到他们的 Windows Azure 应用程序中。</p>-->
<h3 class="feature"><span>功能指南：</span><a href="/zh-cn/develop/net/how-to-guides/twilio-voice-and-sms-service/">Twilio 音频和 SMS 服务</a></h3>
<p>Windows Azure 应用程序可以通过 Twilio 合并电话和短信服务 (SMS) 消息功能。可使用 Twilio API 拨打和接听电话，收发短信，以及通过现有互联网连接（包括移动连接）进行语音通信。</p>
<h2>图像处理</h2>
<h3 class="feature"><span>功能指南：</span><a href="/zh-cn/develop/net/how-to-guides/blitline-image-processing-service/">Blitline 图像处理服务</a></h3>
<p>Blitline 是一项基于云计算的图像处理服务。本指南介绍如何访问 Blitline 服务以及如何将作业提交到 Blitline。</p>
<!--<h2>媒体</h2>
<h3 class="feature"><span>功能指南：</span><a href="/zh-cn/develop/net/how-to-guides/media-services/">媒体服务</a></h3>
<p>Windows Azure 媒体服务在 Windows Azure 上提供了一个可扩展的媒体平台。可使用媒体服务组件完成上传、存储、编码和流式传输内容等任务。可以利用系统端到端或将单个组件与您的现有工具和流程进行集成。</p> -->
<h2>消息传送和集成</h2>
<h3 class="feature"><span>功能指南：</span><a href="/zh-cn/develop/net/how-to-guides/service-bus-queues/">Service Bus 队列</a></h3>
<p>Service Bus 队列提供简单且有保证的先入先出消息传送策略，支持一系列标准协议（REST、AMQP 和 WS*）以及用于将消息放入/推出队列的 API。</p>
<h3 class="feature"><span>功能指南：</span><a href="/zh-cn/develop/net/how-to-guides/service-bus-topics/">Service Bus 主题</a></h3>
<p>Service Bus 主题提供发布/订阅消息传送模型，以支持一对多通信。您可以选择以每个订阅为基础注册主题的筛选规则，这样就能限制哪些主题订阅接收某个主题下的哪些消息。</p>
<h3 class="feature"><span>功能指南：</span><a href="/zh-cn/develop/net/how-to-guides/queue-service/">Windows Azure 队列服务</a></h3>
<p>Windows Azure 队列可存储大量消息，用户可以通过经验证的呼叫，使用 HTTP 或 HTTPS 从世界任何地方访问这些消息。队列存储的常见用途包括：创建积压工作以进行异步处理，从 Windows Azure Web 角色向 Windows Azure 辅助角色传递消息。</p>
<h3 class="feature"><span>功能指南：</span><a href="/zh-cn/develop/net/how-to-guides/service-bus-relay/">Service Bus 中继</a></h3>
<p>Service Bus 中继允许本地 Web 服务设计公共终结点，从而解决了本地应用程序和外界之间的通信难题。之后，系统可访问这些 Web 服务，后者将继续在世界各地的任何位置以本地方式运行。</p>
<h3 class="guidance"><span>指南：</span><a href="/zh-cn/develop/net/how-to-guides/service-bus-amqp-overview">Windows Azure Service Bus 中的 AMQP 1.0 支持</a></h3>
<p>高级消息队列协议 (AMQP) 1.0 是一个高效、可靠的线级消息传送协议，可用于构建强大、跨平台的消息传送应用程序。本文概述了 Service Bus 中的 AMQP 1.0 支持，该支持服务允许您使用开放标准协议构建跨平台的混合应用程序。</p>
<h3 class="feature"><span>功能指南：</span><a href="/zh-cn/develop/net/how-to-guides/service-bus-amqp">Service Bus AMQP</a></h3>
<p>此操作方法指南说明如何通过 .NET API 从 AMQP 1.0 使用 Service Bus 中转消息传递功能（队列和发布/订阅主题）。</p>
<h3 class="guidance"><span>指南：</span><a href="/zh-cn/develop/net/how-to-guides/service-bus-notification-hubs/">Service Bus 通知中心</a></h3>
<p>Service Bus 通知中心可向移动平台提供可扩展的多平台推送通知。本文大致介绍通知中心功能。</p>
<h3 class="feature"><span>功能指南：</span><a href="http://go.microsoft.com/fwlink/?LinkID=275828">Service Bus 通知中心</a></h3>
<p>Service Bus 通知中心可向移动平台提供可扩展的多平台推送通知。它们可在设备注册中提供动态标签、完全与平台无关的后端代码和安全的设备注册。本指南介绍如何利用关键通知中心功能为移动应用开发 .NET 后端。</p>
<h3 class="tutorial"><span>教程：</span><a href="/zh-cn/develop/net/tutorials/multi-tier-application/">使用服务总线队列构建 .NET 多层应用程序</a></h3>
<p>构建一个前端 ASP.NET MVC Web 角色，该角色使用后端辅助角色来处理长时间运行的作业。您将学习如何创建和部署多角色解决方案，以及如何使用服务总线队列和主题来实现角色间通信。</p>
<h3 class="tutorial"><span>教程：</span><a href="/zh-cn/develop/net/tutorials/hybrid-solution/">使用 Service Bus 中继构建 .NET 本地/云混合应用程序</a></h3>
<p>构建在云中托管的混合应用程序并访问存储在本地的数据。您将学习如何使用服务总线中转功能在内部部署和云之间进行通信。</p>
<h3 class="tutorial"><span>教程：</span><a href="/zh-cn/develop/net/tutorials/multi-tier-web-site/1-overview/">使用存储表、队列和 Blob 的 .NET 多层应用程序</a></h3>
<p>该系列教程详细介绍了如何构建使用 Windows Azure 队列在 Web 角色和辅助角色之间进行通信的多层 ASP.NET Web 应用程序。</p>
<h2>监视和管理</h2>
<h3 class="feature"><span>功能指南：</span><a href="/zh-cn/develop/net/how-to-guides/new-relic/">New Relic</a></h3>
<p>New Relic 是以开发人员为主的工具，用于监视生产应用程序，并使用户能够深入了解应用程序的性能和可靠性。其目的在于缩短您识别和诊断性能问题的时间，并使您能够轻松获得解决这些问题所需的信息。</p>
<h3 class="feature"><span>功能指南：</span><a href="/zh-cn/develop/net/how-to-guides/autoscaling/">自动扩展应用程序块</a></h3>
<p>用于 Windows Azure 的 Microsoft Enterprise Library 5.0 集成包中的“自动扩展应用程序块”功能提供使您能够自动扩展云服务的工具。您可以使用性能计数器来了解应用程序的性能，然后编写将自动扩展您的应用程序以根据指定目标和阈值进行调整的规则。</p>]]></bodyText><umbracoNaviHide>0</umbracoNaviHide><pageTitle>app services</pageTitle><metaKeywords></metaKeywords><metaDescription><![CDATA[]]></metaDescription><linkid>app services</linkid><urlDisplayName>app services</urlDisplayName><headerExpose></headerExpose><footerExpose></footerExpose><disqusComments>0</disqusComments><metaCanonical></metaCanonical><isHeader>0</isHeader><pageTemplate></pageTemplate><localize>0</localize><localizePartial>0</localizePartial><sitemapHide>0</sitemapHide><headerText><![CDATA[]]></headerText></umbTextpage></localize>