<?xml version="1.0" encoding="UTF-8"?>
<localize><umbTextpage id="19491" parentID="11978" level="2" writerID="94" creatorID="94" nodeType="1059" template="1052" sortOrder="19" createDate="2014-10-15T11:16:08" updateDate="2014-10-15T11:18:57" nodeName="HeaderConfig" urlName="headerconfig" writerName="xunfan" creatorName="xunfan" path="-1,11978,19491" isDoc=""><bodyText><![CDATA[<div id="headerconfig">
<ul class="dev-navigation">
<li class="nav-expander"><a href="#solutions" class="trigger ">解决方案</a>
<div class="nav-expander-wrapper">
<div class="nav-expander-div">
<div>
<ul>
<li class="nav-has-submenu default"><a href="#">解决方案</a>
<div class="nav-submenu">
<ul>
<li><a href="/solutions/infrastructure/">基础结构服务</a></li>
<li><a href="/solutions/data-management/">数据管理</a></li>
<li><a href="/solutions/web/">Web 应用程序</a></li>
<li><a href="/solutions/dev-test/">开发和测试</a></li>
<li><a href="/solutions/storage-backup-recovery/">存储、备份和恢复</a></li>
<li><a href="/solutions/OSS/">开源解决方案</a></li>
</ul>
</div>
</li>
<li class="nav-has-submenu"><a href="#">功能</a>
<div class="nav-submenu">
<ul>
<li>计算</li>
<li><a href="/home/features/virtual-machines/">虚拟机</a></li>
<li><a href="/home/features/web-site/">网站</a></li>
<li><a href="/home/features/cloud-services/">云服务</a></li>
<li><a href="/home/features/mobile-services/">移动服务</a></li>
</ul>
<ul>
<li>数据服务</li>
<li><a href="/home/features/storage/">存储</a></li>
<li><a href="/home/features/storage/">SQL database</a></li>
<li><a href="/home/features/hdinsight/">HDInsight</a></li>
</ul>
<ul>
<li>应用服务</li>
<li><a href="/home/features/service-bus/">Service Bus</a></li>
<li><a href="/home/features/active-directory/">Active Directory</a></li>
<li><a href="/home/features/caching/">CDN</a></li>
<li><a href="/home/features/media-services/">媒体服务</a></li>
</ul>
<ul>
<li>网络服务</li>
<li><a href="/home/features/virtual-network/">虚拟网络</a></li>
<li><a href="/home/features/traffic-manager/">Traffic Manager</a></li>
</ul>
</div>
</li>
<li class="nav-has-submenu"><a href="#">用户类型</a>
<div class="nav-submenu">
<ul>
<li><a href="/home/usertypes/program/isv/">软件供应商</a></li>
<li><a href="/home/usertypes/program/developer/">开发者</a></li>
<li><a href="/home/usertypes/program/enterprise/">企业用户</a></li>
</ul>
</div>
</li>
</ul>
</div>
</div>
</div>
</li>
<li class="nav-expander"><a href="#pricing" class="trigger">价格</a>
<div class="nav-expander-wrapper">
<div class="nav-expander-div">
<div>
<ul>
<li><a href="/pricing/overview/">价格概览</a></li>
<li><a href="/pricing/calculator/">价格计算器</a></li>
<li class="nav-has-submenu"><a href="#">详细价格</a>
<div class="nav-submenu">
<ul>
<li>计算</li>
<li><a href="/pricing/details/virtual-machines/">虚拟机</a></li>
<li><a href="/pricing/details/web-sites/">网站</a></li>
<li><a href="/pricing/details/cloud-services/">云服务</a></li>
<li><a href="/pricing/details/mobile-services/">移动服务</a></li>
</ul>
<ul>
<li>数据服务</li>
<li><a href="/pricing/details/storage/">存储</a></li>
<li><a href="/pricing/details/sql-database/">SQL Database</a></li>
<li><a href="/pricing/details/hdinsight/">HDInsight</a></li>
</ul>
<ul>
<li>应用服务</li>
<li><a href="/pricing/details/service-bus/">Service Bus</a></li>
<li><a href="/pricing/details/media-services/">媒体服务</a></li>
</ul>
<ul>
<li>网络服务</li>
<li><a href="/pricing/details/virtual-network/">虚拟网络</a></li>
<li><a href="/pricing/details/data-transfer/">数据传输</a></li>
<li><a href="/pricing/details/ip-addresses/">保留IP地址</a></li>
<li><a href="/pricing/details/traffic-manager/">Traffic Manager</a></li>
</ul>
</div>
</li>
</ul>
</div>
</div>
</div>
</li>
<li class="nav-expander"><a href="#pricing" class="trigger">案例与伙伴</a>
<div class="nav-expander-wrapper">
<div class="nav-expander-div">
<div>
<ul>
<li><a href="/partnerancasestudy/case-studies/">案例研究</a></li>
<li><a href="/partnerancasestudy/partner/">合作伙伴</a></li>
</ul>
</div>
</div>
</div>
</li>
<li class="nav-expander"><a href="/starter-guide/">入门指南<sup style="color: #f05a28; font-size: 120%;">●</sup></a></li>
<li class="nav-expander"><a href="#documentation" class="trigger">技术文档</a>
<div class="nav-expander-wrapper">
<div class="nav-expander-div">
<div>
<ul>
<li><a href="https://docs.azure.cn/">文档概览</a></li>
<li class="nav-has-submenu default"><a href="#">功能文档</a>
<div class="nav-submenu">
<ul>
<li>计算</li>
<li><a href="/manage/windows/">虚拟机 - Windows</a></li>
<li><a href="/manage/linux/">虚拟机 - Linux</a></li>
<li><a href="/manage/services/web-sites/">网站</a></li>
<li><a href="/manage/services/cloud-services/">云服务</a></li>
<li><a href="/manage/services/mobile-services/">移动服务</a></li>
</ul>
<ul>
<li>数据服务</li>
<li><a href="/manage/services/storage/">存储</a></li>
<li><a href="/manage/services/sql-databases/">SQL Database</a></li>
<li><a href="/manage/services/hdinsight/">HDInsight</a></li>
</ul>
<ul>
<li>应用服务</li>
<li><a href="/manage/services/service-bus/">Service Bus</a></li>
<li><a href="/manage/services/identity/">Active Directory</a></li>
<li><a href="/services/scheduler/">计划程序</a></li>
<li><a href="/manage/services/cdn/">CDN</a></li>
<li><a href="/develop/media-services/">媒体服务</a></li>
</ul>
<ul>
<li>网络服务</li>
<li><a href="/manage/services/networking/">虚拟网络</a></li>
<li><a href="/manage/services/networking/traffic-manager/">Traffic Manager</a></li>
</ul>
</div>
</li>
<li class="nav-has-submenu"><a href="#">开发文档</a>
<div class="nav-submenu">
<ul>
<li>语言</li>
<li><a href="/develop/net/">.Net</a></li>
<li><a href="/develop/java/">Java</a></li>
<li><a href="/develop/nodejs/">Node.js</a></li>
<li><a href="/develop/python/">Python</a></li>
</ul>
</div>
</li>
<li class="nav-has-submenu"><a href="#">资源</a>
<div class="nav-submenu">
<ul>
<li>资源</li>
<li><a href="/develop/net/architecture/">架构指南</a></li>
<li><a href="/develop/other/developerdifferences/">开发说明</a></li>
<li><a href="/develop/other/open-source-software/">开源软件</a></li>
</ul>
</div>
</li>
</ul>
</div>
</div>
</div>
</li>
<li class="nav-expander"><a href="#downloads" class="trigger">工具下载</a>
<div class="nav-expander-wrapper">
<div class="nav-expander-div">
<div>
<ul>
<li class="nav-has-submenu default"><a href="#">SDK</a>
<div class="nav-submenu">
<ul>
<li><a href="/downloads/?sdk=net">.Net</a></li>
<li><a href="/downloads/?sdk=node">Node.js</a></li>
<li><a href="/downloads/?sdk=php">PHP</a></li>
<li><a href="/downloads/?sdk=java">Java</a></li>
</ul>
<ul>
<li><a href="/downloads/?sdk=python">Python</a></li>
</ul>
</div>
</li>
<li><a href="/downloads/#cmd-line-tools">命令行工具</a></li>
</ul>
</div>
</div>
</div>
</li>
<li class="nav-expander"><a href="#community" class="trigger">社区</a>
<div class="nav-expander-wrapper">
<div class="nav-expander-div">
<div>
<ul>
<li><a href="/community/events/">活动</a></li>
<li><a href="/community/blog/">博客</a></li>
<li><a href="/community/newsletter/">每月公告</a></li>
</ul>
</div>
</div>
</div>
</li>
<li class="nav-expander"><a href="#support" class="trigger">支持</a>
<div class="nav-expander-wrapper">
<div class="nav-expander-div">
<div>
<ul>
<li><a href="/support/contact/">联系我们</a></li>
<li><a href="/support/plans/">支持计划</a></li>
<li><a href="/support/service-dashboard/">服务仪表盘</a></li>
<li><a href="/support/trust-center/">信任中心</a></li>
<li><a href="/support/legal/">法律</a></li>
<li><a href="/support/faq/">常见问题</a></li>
</ul>
</div>
</div>
</div>
</li>
<li class="nav-expander"><a href="/what-is-new/">最新公告<sup style="color: #f05a28; font-size: 120%;">●</sup></a></li>
</ul>
</div>]]></bodyText><umbracoNaviHide>0</umbracoNaviHide><pageTitle>header config</pageTitle><metaKeywords></metaKeywords><metaDescription><![CDATA[]]></metaDescription><linkid>headerconfig</linkid><urlDisplayName>header config</urlDisplayName><headerExpose></headerExpose><footerExpose></footerExpose><disqusComments>0</disqusComments><metaCanonical></metaCanonical><isHeader>0</isHeader><pageTemplate></pageTemplate><localize>0</localize><localizePartial>0</localizePartial><sitemapHide>0</sitemapHide><headerText><![CDATA[]]></headerText><forbidPublish>1</forbidPublish></umbTextpage></localize>