<?xml version="1.0" encoding="UTF-8"?>
<localize><umbTextpage id="12034" parentID="12022" level="3" writerID="94" creatorID="22" nodeType="1059" template="1052" sortOrder="4" createDate="2012-05-29T21:02:15" updateDate="2014-09-22T11:48:58" nodeName="Free Trial" urlName="free-trial" writerName="xunfan" creatorName="Brad" path="-1,11978,12022,12034" isDoc=""><bodyText><![CDATA[<div style="margin-left: -90px; margin-right: -90px;">
<div style="background-color: #00abec; background-image: url('/css/images/_background_free_trial.png'); background-repeat: no-repeat; background-position: right; height: 320px; padding-bottom: 55px; padding-top: 55px; padding-right: 90px; padding-left: 90px;">
<div class="_freetrial-bannerh1"><span>最专业的公有云平台</span><br /><span>Windows Azure 在线直付公开预览</span></div>
<div class="_freetrial-bannerh2">欢迎您加入 Windows Azure在线直付 （Webdirect）的公开预览，我们很快将开启更为灵活方便的Windows Azure 体验与购买方式。请点下方按钮开始加入 1元试用计划。开始您的Windows Azure体验。</div>
<div class="_freetrial-linkbutton-green" style="width: 210px;"><a id="_azure-trial-button" href="/zh-cn/pricing/free-trial-application-form/" class="_freetrial-link3" onclick="return RioTracking.click(300189254);"> 申请试用</a></div>
<a id="_homepage-linkwhite2" href="/zh-cn/pricing/enter-promo-code-form/"> 或输入激活码</a></div>
<div style="padding-top: 50px; padding-bottom: 50px; padding-left: 90px; padding-right: 90px;">
<h2 class="pagetitle">Windows Azure 1元试用 公开预览</h2>
<p class="pagecontent">预览期间，我们将向1500位用户提供 一个月的试用期：通过在线方式注册并付款 1 元人民币，您即可得到高达 2,000 元人民币的Windows Azure用量积分，有效期一个月。 试用期间， 如果您决定购买成为正式用户， 可随时通过标准预付费方式在线购买。</p>
<p class="pagecontent">请注意：</p>
<ol>
<li>在预览期间，用量享受5折优惠，相当于获得4000元额度（系统中任然显示2000元积分）。</li>
<li>目前，续费成为正式用户时需要使用您在注册缴付1元人民币时相同的支付方式和账号。即在正式商用前，您暂时不能中途变更充值支付方式。</li>
</ol>
<p class="pagecontent">每位新客户仅有一次享受本优惠的机会。</p>
<h2 class="pagetitle">灵活的Windows Azure 积分</h2>
<p class="pagecontent">在得到试用账号时您将获得 2,000 元人民币的 Azure 积分。您可以选择如何使用您的 Azure 积分。可将这些积分用在满足您需要的 Azure 服务上，包括虚拟机、云服务、存储、SQL 数据库等很多方面。以下是几个在 1 个月时间内消耗不超过 2,000 元人民币积分的使用方案：</p>
<ul>
<li>全月运行 4 个小型虚拟机实例；或</li>
<li>在跨地域冗余存储中存储 3 TB 数据；或</li>
<li>开发和测试使用云服务的 Web 应用程序，在中型实例上设置 3 个 Web role 和 2 个 Worker role，按一天 10 小时，一周 5 天计算；或</li>
<li>全月运行一个 300 GB 的 SQL 数据库商业版</li>
</ul>
<p class="pagecontent">预览期间，试用资源享受5折优惠。</p>
<h2 class="pagetitle">试用账号配额</h2>
<p class="pagecontent">适用以下月度使用配额。如果您需要的额度超出这些配额，请随时联系我们的<a href="http://www.windowsazure.cn/zh-cn/support/contact/">客户服务</a>，我们将根据您的实际需求情况相应调整配额。</p>
<h2 class="pagetitle">云服务和虚拟机</h2>
<p class="pagecontent">标准配额为 4 个并发标准小型 (A1) 计算实例，或同等数量的其他类型或大小的计算实例，通过下列计算实例配额换算表予以确定。</p>
<table border="0" class="common_table" id="free_trial_storage_table">
<thead>
<tr><th class="left_align">计算实例类型</th><th class="left_align">等效标准小型 (A1) 实例数量</th></tr>
</thead>
<tbody>
<tr>
<td>超小型 (A0)</td>
<td>1</td>
</tr>
<tr>
<td>小型 (A1)</td>
<td>2</td>
</tr>
<tr>
<td>中型 (A2)</td>
<td>2</td>
</tr>
<tr>
<td>大型 (A3) 或 A6</td>
<td>4</td>
</tr>
<tr>
<td>超大型 (A4) 或 A7</td>
<td>8</td>
</tr>
</tbody>
</table>
<h2 class="pagetitle">存储</h2>
<p class="pagecontent">2 个并行存储帐户</p>
<h2 class="pagetitle">云服务</h2>
<p class="pagecontent">2 个云服务帐户。每个云服务帐户将拥有 2 个部署环境：Staging 环境和生产环境。</p>
<h2 class="pagetitle">Active Directory</h2>
<p class="pagecontent">150,000 个对象</p>
<p class="pagecontent">一个对象是指目录服务中的一个条目，采用易于识别的唯一名称表示。例如，用于身份验证的用户条目即为一个对象。</p>
<p class="pagecontent">如果您在一个给定月份中超出了上述配额，您还需负责为超出配额的部分付费。我们也将保留在您超过配额当月禁用您帐户的权利，不过我们会在禁用之前通过电子邮件与您联系。</p>
<h2 class="pagetitle">服务级别协议 (SLA)</h2>
<p class="pagecontent">本预览版优惠不提供服务级别协议。</p>
<p class="pagecontent">当服务正式发布后，我们将针对各 Azure 平台服务提供一组强大的服务级别协议。请参见我们的<a href="http://www.windowsazure.cn/zh-cn/support/legal/sla/">SLA 页面</a>，了解更多详情。</p>
<p><a href="/zh-cn/offers/ms-mc-azr-44p/">更多信息请查看</a></p>
</div>
</div>]]></bodyText><umbracoNaviHide>1</umbracoNaviHide><pageTitle>Windows Azure 免费试用：试用 Windows Azure | Azure 免费试用</pageTitle><metaKeywords>Azure 免费试用, 云免费试用, PaaS 免费试用, Windows Azure 免费试用, Microsoft Azure 免费试用</metaKeywords><metaDescription><![CDATA[免费试用 Windows Azure 3 个月，无需承担任何责任。免费获得 750 小时的小型计算时间、1GB SQL Azure 数据库等。]]></metaDescription><linkid>pricing-freetrial</linkid><urlDisplayName>免费试用</urlDisplayName><headerExpose></headerExpose><footerExpose></footerExpose><disqusComments>0</disqusComments><metaCanonical></metaCanonical><isHeader>0</isHeader><pageTemplate>nosecondarynav noportallink switchfreetriallink</pageTemplate><localize>1</localize><localizePartial>0</localizePartial><sitemapHide>0</sitemapHide><headerText><![CDATA[]]></headerText><forbidPublish>0</forbidPublish></umbTextpage></localize>