<?xml version="1.0" encoding="utf-8" ?>
<localize>
  <umbTextpage id="2015090214" parentID="11978" level="2" writerID="106" creatorID="22" nodeType="1059" template="302" sortOrder="5" createDate="2015-09-02T13:16:52" updateDate="2015-09-02T13:16:52" nodeName="silvercat" urlName="silvercat" writerName="content" creatorName="Brad" path="-1,11978,11979,13946,2015090214" isDoc="" isResponsive="true">
    <bodyText>
      <![CDATA[
<style>
    .mian-content {
        width: 100%;
    }

    .distance {
        margin-left: 20px;
    }

    h1 {
        margin-bottom: 0px;
    }
    /*banner 内容*/
    .startups-banner {
        background: url(//wacndevelop.blob.core.chinacloudapi.cn/marketing-resource/css/images/jinyinmaobanner.png) no-repeat scroll center center;
        display: block;
        width: 100%;
        padding: 0;
        border: none;
        position: relative;
        z-index: 0;
        height: 220px;
        background-color: #48c1b3;
    }

        .startups-banner h1 {
            margin-top: 50px;
            font-size: 36px;
            color: #ffffff;
            margin-bottom: 35px;
            line-height: 54px;
            padding: 0px;
        }

        .startups-banner h2 {
            font-size: 14px;
            color: #c8f3ee;
            /*margin-bottom: 36px;*/
            max-width: 580px;
        }

    .banner-content {
        overflow: hidden;
        box-sizing: border-box;
        -moz-box-sizing: border-box;
        -webkit-box-sizing: border-box;
        min-width: 960px;
        max-width: 1200px;
        margin: 0 auto;
    }

    .btn-style {
        color: #fff;
        display: block;
        width: 142px;
        height: 38px;
        background-color: #ff3d00;
        left: 50%;
        line-height: 38px;
        text-align: center;
    }

        .btn-style:hover {
            background-color: #fa6434;
        }
    /*主要内容*/
    .startups-content {
        overflow: hidden;
        box-sizing: border-box;
        -moz-box-sizing: border-box;
        -webkit-box-sizing: border-box;
        min-width: 960px;
        max-width: 1200px;
        margin: 0 auto;
    }

    .silvercat-title {
        font-size: 36px;
        color: #323a45;
        clear: both;
        line-height:54px;
    }
    /*内容样式*/
    .content-style {
        font-size: 14px;
        color: #5e6d81;
        line-height:22px;
    }
</style>
<div class="mian-content">
    <!--banner部分-->
    <div class="startups-banner">
        <div class="banner-content">
            <div class="distance">
                <h1>
                    <a id="silvercat_cloud" class="anchor"></a>
                    让我们共同创造奇迹
                </h1>
                <h2>微软携手金银猫为您打造限时优惠方案</h2>
                <div>
                    <!--<a class="btn-style" id="silvercat_banner_join" target="_blank" href="/isv" style="color:#fff;">立刻加入</a>-->
                </div>
            </div>
        </div>
    </div>
    <!--内容部分-->
    <div class="startups-content">
        <div class="distance">
            <div class="cloud-content">
                <h1 class="silvercat-title" style="padding-bottom: 30px; padding-top: 80px;">
                    <a id="silvercat_name" class="anchor"></a>
                    亲爱的金银猫用户，
                </h1>
                <div class="content-style">
                    <span style="font-size: 16px;color: #000;font-weight: 600; clear: both;">好消息！</span>如果您还不是 Azure 的客户，在9月10日至9月24日期间充值，您将享受如下的限时优惠！
                </div>
                <div class="content-style" style="padding-top: 10px;font-weight:600;padding-left:20px;">
                    1. 充值人民币2000元，另获赠人民币2500元信用额度；
                </div>
                <div class="content-style" style=" font-weight:600;padding-left:20px;"  >
                   2. 充值人民币5000元，另获赠人民币5000元信用额度；
                </div>
                  <div class="content-style" style="padding-bottom: 5px; font-weight:600;padding-left:20px;">
                  3. 充值人民币10000元，另获赠人民币10000元信用额度；
                </div>

                <div class="content-style" style="padding: 5px 0px;">
                    请<a id="silvercat_mail_auswang"  target="_blank;" style="color: #00a8d9;" href="mailto:v-jichba@microsoft.com?subject=Apply%20for%20Azure%20promotion&body=亲爱的金银猫客户，%0a%0a如果您还不是微软 Windows Azure 的客户，如果您在9月10日至9月24日期间充值，您将享受到限时超值优惠！%0a%0a请正确填写并完成下述信息，我们的业务代表会尽快与您联系。%0a%0a必填项%0a%20%20%20%20%20•%20公司名称：%0a%20%20%20%20%20•%20客户姓名：%0a%20%20%20%20%20•%20手机：%0a%20%20%20%20%20•%20优惠项目（选择1-3项）：%0a可选项%0a%20%20%20%20%20•%20邮箱：%0a%20%20%20%20%20•%20地址：%0a%20%20%20%20%20•%20公司电话：%0a%0a非常感谢！">发送您的联系方式</a>，我们的业务代表会在第一时间拨打您的联系电话（工作电话或手机）与您联系，在确认您是 Azure 新客户后，我们将会发送优惠活动代码到您的电子邮箱。如有需要我们会帮助您完成优惠代码的使用。
                      </div>
                     <div class="content-style" style="padding-top:20px;">                   
                    由世纪互联运营的<a id="silvercat_what_windows_Azure"  target="_blank;" style="color: #00a8d9;" href="/home/features/what-is-windows-azure/"> Azure </a>作为目前唯一落地中国的国际公有云，为众多中国企业客户和个人客户提供了安全、可靠且可扩展的云服务平台。您可以通过微软公有云服务实现部署和开发应用程序、<a id="silvercat_home_web-site"  target="_blank;" style="color: #00a8d9;" href="/home/features/web-site/">网站</a>、<a id="silvercat_"  target="_blank;" style="color: #00a8d9;" href="/home/features/hdinsight/">大数据</a>、物联网、<a id="silvercat_home_mobile-services"  target="_blank;" style="color: #00a8d9;" href="/home/features/mobile-services/">移动 APP</a>、<a id="silvercat_home_backup"  target="_blank;" style="color: #00a8d9;" href="/home/features/backup/">备份</a>和<a id="silvercat_home_site-recovery"  target="_blank;" style="color: #00a8d9;" href="/home/features/site-recovery/">容灾</a>等随时、随地，并根据需要而提供的公共服务，使来自中国的众多客户收益：
                </div>
                            
                <div class="content-style">
                    <ul style="margin: 10px 0px;">
                        <li>低成本：众多用户不必花费时间和资金完成建立基础设施的时间，成本的花费。</li>
                        <li>开放而灵活：您可以随心利用 Windows 和 Linux 生态系统构建能够在任何设备上运行的完美应用程序和服务。</li>
                        <li>应用而非运营：可以使企业或个人集中用于帮助企业发展的项目上。</li>
                        <li>扩展和灵敏：企业和个人可以在几分钟内部署数十、甚至数百个计算节点，而无需任何琐碎的流程。</li>
                        <li>随时加入混合部署：微软Azure 是经企业验证的混合云解决方案，可以扩展您的业务，而且还不会提高复杂性。</li>
                    </ul>
                </div>
            </div>
        </div>

    </div>
    <div style="padding-top:60px;">
        <hr style="overflow: hidden;margin:0px;padding:0px;" />
    </div>
    <div class="startups-content">
        <div class="distance">
            <h1 class="silvercat-title" style="margin:50px 0px 30px 0px">
                <a id="silvercat_name" class="anchor"></a>
                本次合作伙伴
            </h1>
            <div class="content-left" style="float:left;margin-right:50px;margin-bottom:100px;">
                <img src="//wacndevelop.blob.core.chinacloudapi.cn/marketing-resource/css/images/UGIcons/jymlogo_03.png"/>
            </div>
            <div class="content-right">
                <div>上海金银猫金融服务有限公司（以下简称“金银猫”）成立于2013年9月，是国内首创以“P2B+O2O”为经营模式的新型互联网金融服务公司。</div>
                <div>金银猫以票据理财特有的安全性，流动性及未来票据电子化的发展趋势找到了突破口，以票据作为切入互联网金融的重要抓手。区别于传统的 P2P 网贷平台，金银猫坚持建设成为一个互联网金融服务平台。依靠银行承兑汇票天然具有的增信效果，金银猫能够以服务者的形象成为连接投资者和融资企业之间的桥梁。</div>
                <div>
                    金银猫成功树立了互联网票据理财第一品牌，并正在引领互联网理财新方向。
                </div>
                <div>
                    金银猫金融服务有限公司是一家创新型的互联网金融理财平台。是国内最大的互联网票据理财平台。由于平台正处于高速发展期，平台的访问量与日俱增，技术维护难度也越来越大。因此金银猫使用了 Azure 公有云服务，使平台运行更稳定，客户访问更流畅，优化了用户体验。
                </div>
            </div>
        </div>
    </div>
    ]]>

    </bodyText>
    <umbracoNaviHide>0</umbracoNaviHide>
	<redirectURL></redirectURL>
    <pageTitle> 金银猫 - Azure 微软云</pageTitle>
    <metaKeywords></metaKeywords>
    <metaDescription><![CDATA[]]></metaDescription>
    <linkid>silvercat</linkid>
    <urlDisplayName>silvercat</urlDisplayName>
    <headerExpose />
    <footerExpose />
    <disqusComments>0</disqusComments>
    <metaCanonical />
    <isHeader>0</isHeader>
    <pageTemplate />
    <localize>0</localize>
    <localizePartial>0</localizePartial>
    <sitemapHide>0</sitemapHide>
    <headerText><![CDATA[]]></headerText>
    <forbidPublish>0</forbidPublish>
  </umbTextpage>
</localize>